multitranslator/__init__.py
multitranslator/__version__.py
multitranslator/exceptions.py
multitranslator/translators/__init__.py
multitranslator/translators/cambridge.py
multitranslator/translators/fastdict.py
multitranslator/translators/multi.py
multitranslator/translators/translator.py
multitranslator-0.0.2.dist-info/LICENSE
multitranslator-0.0.2.dist-info/METADATA
multitranslator-0.0.2.dist-info/WHEEL
multitranslator-0.0.2.dist-info/top_level.txt
multitranslator-0.0.2.dist-info/RECORD
