Metadata-Version: 2.1
Name: multitranslator
Version: 0.0.2
Summary: Multi translation engine for Python
Home-page: https://github.com/GreatBahram/multitranslator
Author: Bahram Aghaei
Author-email: aghaee.bahram@gmail.com
License: GNU General Public License v3.0
Platform: UNKNOWN
Classifier: Intended Audience :: Developers
Classifier: Programming Language :: Python :: 3 :: Only
Classifier: Programming Language :: Python :: 3.6
Classifier: Programming Language :: Python :: 3.7
Requires-Dist: requests
Requires-Dist: bs4
Requires-Dist: lxml
